pathway/__init__.py
pathway/__main__.py
pathway/_engine_finder.py
pathway/cli.py
pathway/conftest.py
pathway/debug/__init__.py
pathway/demo/__init__.py
pathway/engine.abi3.so
pathway/engine.pyi
pathway/internals/__init__.py
pathway/internals/_io_helpers.py
pathway/internals/api.py
pathway/internals/arg_handlers.py
pathway/internals/arg_tuple.py
pathway/internals/column.py
pathway/internals/column_namespace.py
pathway/internals/column_path.py
pathway/internals/column_properties.py
pathway/internals/common.py
pathway/internals/config.py
pathway/internals/custom_reducers.py
pathway/internals/datasink.py
pathway/internals/datasource.py
pathway/internals/datetime_types.py
pathway/internals/decorators.py
pathway/internals/deprecation_meta.py
pathway/internals/desugaring.py
pathway/internals/dtype.py
pathway/internals/errors.py
pathway/internals/expression.py
pathway/internals/expression_printer.py
pathway/internals/expression_props_evaluator.py
pathway/internals/expression_visitor.py
pathway/internals/expressions/__init__.py
pathway/internals/expressions/date_time.py
pathway/internals/expressions/numerical.py
pathway/internals/expressions/string.py
pathway/internals/fingerprints.py
pathway/internals/graph_runner/__init__.py
pathway/internals/graph_runner/async_utils.py
pathway/internals/graph_runner/expression_evaluator.py
pathway/internals/graph_runner/operator_handler.py
pathway/internals/graph_runner/path_evaluator.py
pathway/internals/graph_runner/path_storage.py
pathway/internals/graph_runner/row_transformer_operator_handler.py
pathway/internals/graph_runner/scope_context.py
pathway/internals/graph_runner/state.py
pathway/internals/graph_runner/storage_graph.py
pathway/internals/graph_runner/telemetry.py
pathway/internals/groupbys.py
pathway/internals/helpers.py
pathway/internals/interactive.py
pathway/internals/join_mode.py
pathway/internals/joins.py
pathway/internals/json.py
pathway/internals/monitoring.py
pathway/internals/operator.py
pathway-0.29.0.dist-info/METADATA
pathway-0.29.0.dist-info/WHEEL
pathway-0.29.0.dist-info/entry_points.txt
pathway-0.29.0.dist-info/licenses/LICENSE.txt
pathway-0.29.0.dist-info/licenses/LICENSE_abomonation-LICENSE-MIT
pathway-0.29.0.dist-info/licenses/LICENSE_adler2-LICENSE-0BSD
pathway-0.29.0.dist-info/licenses/LICENSE_adler2-LICENSE-APACHE
pathway-0.29.0.dist-info/licenses/LICENSE_adler2-LICENSE-MIT
pathway-0.29.0.dist-info/licenses/LICENSE_adler32-LICENSE-ZLIB
pathway-0.29.0.dist-info/licenses/LICENSE_ahash-LICENSE-APACHE
pathway-0.29.0.dist-info/licenses/LICENSE_ahash-LICENSE-MIT
pathway-0.29.0.dist-info/licenses/LICENSE_aho-corasick-LICENSE-MIT
pathway-0.29.0.dist-info/licenses/LICENSE_airbyte_serverless-LICENSE-MIT
pathway-0.29.0.dist-info/licenses/LICENSE_alloc-no-stdlib-LICENSE-BSD
pathway-0.29.0.dist-info/licenses/LICENSE_alloc-stdlib-LICENSE-BSD
pathway-0.29.0.dist-info/licenses/LICENSE_allocator-api2-LICENSE-APACHE
pathway-0.29.0.dist-info/licenses/LICENSE_allocator-api2-LICENSE-MIT
pathway-0.29.0.dist-info/licenses/LICENSE_anyhow-LICENSE-APACHE
pathway-0.29.0.dist-info/licenses/LICENSE_anyhow-LICENSE-MIT
pathway-0.29.0.dist-info/licenses/LICENSE_apache-avro-LICENSE-APACHE
pathway-0.29.0.dist-info/licenses/LICENSE_arc-swap-LICENSE-APACHE
pathway-0.29.0.dist-info/licenses/LICENSE_arc-swap-LICENSE-MIT
pathway-0.29.0.dist-info/licenses/LICENSE_arcstr-LICENSE-APACHE
pathway-0.29.0.dist-info/licenses/LICENSE_arcstr-LICENSE-MIT
pathway-0.29.0.dist-info/licenses/LICENSE_arcstr-LICENSE-ZLIB
pathway-0.29.0.dist-info/licenses/LICENSE_array-init-LICENSE-APACHE
pathway-0.29.0.dist-info/licenses/LICENSE_array-init-LICENSE-MIT
pathway-0.29.0.dist-info/licenses/LICENSE_arrayref-LICENSE-BSD
pathway-0.29.0.dist-info/licenses/LICENSE_arrayvec-LICENSE-APACHE
pathway-0.29.0.dist-info/licenses/LICENSE_arrayvec-LICENSE-MIT
pathway-0.29.0.dist-info/licenses/LICENSE_arrow-LICENSE-APACHE
pathway-0.29.0.dist-info/licenses/LICENSE_arrow-arith-LICENSE-APACHE
pathway-0.29.0.dist-info/licenses/LICENSE_arrow-array-LICENSE-APACHE
pathway-0.29.0.dist-info/licenses/LICENSE_arrow-buffer-LICENSE-APACHE
pathway-0.29.0.dist-info/licenses/LICENSE_arrow-cast-LICENSE-APACHE
pathway-0.29.0.dist-info/licenses/LICENSE_arrow-csv-LICENSE-APACHE
pathway-0.29.0.dist-info/licenses/LICENSE_arrow-data-LICENSE-APACHE
pathway-0.29.0.dist-info/licenses/LICENSE_arrow-ipc-LICENSE-APACHE
pathway-0.29.0.dist-info/licenses/LICENSE_arrow-json-LICENSE-APACHE
pathway-0.29.0.dist-info/licenses/LICENSE_arrow-ord-LICENSE-APACHE
pathway-0.29.0.dist-info/licenses/LICENSE_arrow-row-LICENSE-APACHE
pathway-0.29.0.dist-info/licenses/LICENSE_arrow-schema-LICENSE-APACHE
pathway-0.29.0.dist-info/licenses/LICENSE_arrow-select-LICENSE-APACHE
pathway-0.29.0.dist-info/licenses/LICENSE_arrow-string-LICENSE-APACHE
pathway-0.29.0.dist-info/licenses/LICENSE_assert_matches-LICENSE-APACHE
pathway-0.29.0.dist-info/licenses/LICENSE_assert_matches-LICENSE-MIT
pathway-0.29.0.dist-info/licenses/LICENSE_async-compression-LICENSE-APACHE
pathway-0.29.0.dist-info/licenses/LICENSE_async-compression-LICENSE-MIT
pathway-0.29.0.dist-info/licenses/LICENSE_async-lock-LICENSE-APACHE
pathway-0.29.0.dist-info/licenses/LICENSE_async-lock-LICENSE-MIT
pathway-0.29.0.dist-info/licenses/LICENSE_async-nats-LICENSE-APACHE
pathway-0.29.0.dist-info/licenses/LICENSE_async-stream-LICENSE-MIT
pathway-0.29.0.dist-info/licenses/LICENSE_async-stream-impl-LICENSE-MIT
pathway-0.29.0.dist-info/licenses/LICENSE_async-trait-LICENSE-APACHE
pathway-0.29.0.dist-info/licenses/LICENSE_async-trait-LICENSE-MIT
pathway-0.29.0.dist-info/licenses/LICENSE_atoi-LICENSE-MIT
pathway-0.29.0.dist-info/licenses/LICENSE_atomic-waker-LICENSE-APACHE
pathway-0.29.0.dist-info/licenses/LICENSE_atomic-waker-LICENSE-MIT
pathway-0.29.0.dist-info/licenses/LICENSE_attohttpc-LICENSE
pathway-0.29.0.dist-info/licenses/LICENSE_autocfg-LICENSE-APACHE
pathway-0.29.0.dist-info/licenses/LICENSE_autocfg-LICENSE-MIT
pathway-0.29.0.dist-info/licenses/LICENSE_aws-config-LICENSE-APACHE
