Metadata-Version: 2.4
Name: pathway
Version: 0.29.0
Classifier: License :: Other/Proprietary License
Classifier: Programming Language :: Rust
Classifier: Programming Language :: Python :: Implementation :: CPython
Requires-Dist: aiohttp>=3.10.11
Requires-Dist: click>=8.1
Requires-Dist: geopy>=2.4.0
Requires-Dist: h3>=4
Requires-Dist: numpy>=1.21
Requires-Dist: pandas>=2.1
Requires-Dist: scikit-learn>=1.0
Requires-Dist: shapely>=2.0.1
Requires-Dist: pyarrow>=10.0.0,<19.0.0
Requires-Dist: requests>=2.31.0
Requires-Dist: python-sat>=0.1.8.dev0
Requires-Dist: beartype>=0.14.0,<0.16.0
Requires-Dist: rich>=12.6.0
Requires-Dist: diskcache>=5.2.1
Requires-Dist: exceptiongroup>=1.1.3 ; python_full_version < '3.11'
Requires-Dist: boto3>=1.26.76,<2.0.0
Requires-Dist: google-api-python-client>=2.108.0
Requires-Dist: typing-extensions>=4.8.0
Requires-Dist: panel>=1.3.1
Requires-Dist: jupyter-bokeh>=3.0.7
Requires-Dist: jmespath>=1.0.1
Requires-Dist: aiohttp-cors>=0.7.0
Requires-Dist: opentelemetry-api>=1.22.0
Requires-Dist: opentelemetry-sdk>=1.22.0
Requires-Dist: opentelemetry-exporter-otlp-proto-grpc>=1.22.0
Requires-Dist: fs>=2.4.16
Requires-Dist: async-lru>=2.0.4
Requires-Dist: networkx>=3.2.1
Requires-Dist: google-cloud-pubsub>=2.21.1
Requires-Dist: google-cloud-bigquery~=3.29.0
Requires-Dist: pydantic~=2.9
Requires-Dist: gitpython>=3.1.43
Requires-Dist: deltalake>=0.17.0,<0.18.0
Requires-Dist: sqlalchemy>=2.0.43
Requires-Dist: sqlmodel>=0.0.24
Requires-Dist: fastapi>=0.116.1
Requires-Dist: uvicorn>=0.29.0
Requires-Dist: google-cloud-run ; extra == 'airbyte'
Requires-Dist: google-cloud-secret-manager ; extra == 'airbyte'
Requires-Dist: google-cloud-logging ; extra == 'airbyte'
Requires-Dist: pyyaml ; extra == 'airbyte'
Requires-Dist: jinja2 ; extra == 'airbyte'
Requires-Dist: pathway[sql] ; extra == 'all'
Requires-Dist: pathway[xpack-llm] ; extra == 'all'
Requires-Dist: pathway[xpack-llm-local] ; extra == 'all'
Requires-Dist: pathway[xpack-llm-docs] ; extra == 'all'
Requires-Dist: pathway[xpack-sharepoint] ; extra == 'all'
Requires-Dist: pathway[airbyte] ; extra == 'all'
Requires-Dist: sqlglot==10.6.1 ; extra == 'sql'
Requires-Dist: pytest>=8.0.0,<9.0.0 ; extra == 'tests'
Requires-Dist: pytest-xdist>=3.3.1,<4.0.0 ; extra == 'tests'
Requires-Dist: pytest-rerunfailures>=13.0,<14.0 ; extra == 'tests'
Requires-Dist: pytest-asyncio>=1.2.0 ; extra == 'tests'
Requires-Dist: python-louvain ; extra == 'tests'
Requires-Dist: openapi-spec-validator ; extra == 'tests'
Requires-Dist: kafka-python>=2.0.2 ; extra == 'tests'
Requires-Dist: python-magic ; extra == 'tests'
Requires-Dist: pathway[all] ; extra == 'tests'
Requires-Dist: dill>=0.3.8 ; extra == 'tests'
Requires-Dist: cloudpickle>=3.0.0 ; extra == 'tests'
Requires-Dist: fpdf ; extra == 'tests'
Requires-Dist: paddlepaddle>=3.2.0,<3.3.0 ; extra == 'tests'
Requires-Dist: paddlex>=3.0.0,<=3.3.8 ; extra == 'tests'
Requires-Dist: paddlepaddle>=3.2.0,<4.0.0 ; extra == 'tests'
Requires-Dist: aioboto3>=13.0.0 ; extra == 'tests'
Requires-Dist: openai~=1.60 ; extra == 'xpack-llm'
Requires-Dist: litellm~=1.44,<1.77.3 ; extra == 'xpack-llm'
Requires-Dist: cohere~=5.1 ; extra == 'xpack-llm'
Requires-Dist: tiktoken>=0.5 ; extra == 'xpack-llm'
Requires-Dist: aioboto3>=13.0.0 ; extra == 'xpack-llm'
Requires-Dist: langchain>=0.2.0,<0.4.0 ; extra == 'xpack-llm'
Requires-Dist: langchain-community>=0.2.0,<0.4.0 ; extra == 'xpack-llm'
Requires-Dist: llama-index-core>=0.10.0,<0.13.0 ; extra == 'xpack-llm'
Requires-Dist: llama-index-readers-pathway>=0.1.3 ; extra == 'xpack-llm'
Requires-Dist: llama-index-retrievers-pathway>=0.1.3 ; extra == 'xpack-llm'
Requires-Dist: tenacity!=8.4.0 ; extra == 'xpack-llm'
Requires-Dist: instructor~=1.2 ; extra == 'xpack-llm'
Requires-Dist: google-generativeai~=0.8.4 ; extra == 'xpack-llm'
Requires-Dist: google-api-core~=2.24.1 ; extra == 'xpack-llm'
Requires-Dist: fastmcp>=2.11.0 ; extra == 'xpack-llm'
Requires-Dist: docling>=2.27,<2.67.0 ; extra == 'xpack-llm-docs'
Requires-Dist: docling-core>=2.55,<2.58.0 ; extra == 'xpack-llm-docs'
Requires-Dist: python-docx>=1.1.2 ; extra == 'xpack-llm-docs'
Requires-Dist: unstructured[all-docs]~=0.18.1 ; extra == 'xpack-llm-docs'
Requires-Dist: pdf2image ; extra == 'xpack-llm-docs'
Requires-Dist: pypdf ; extra == 'xpack-llm-docs'
Requires-Dist: pdfminer-six==20250506 ; extra == 'xpack-llm-docs'
Requires-Dist: paddleocr[doc-parser]>=3.3.1,<4.0.0 ; extra == 'xpack-llm-docs'
Requires-Dist: sentence-transformers ; extra == 'xpack-llm-local'
Requires-Dist: transformers>=4.42.0,<=4.49.0 ; extra == 'xpack-llm-local'
Requires-Dist: office365-rest-python-client>=2.5.3 ; extra == 'xpack-sharepoint'
Provides-Extra: airbyte
Provides-Extra: all
Provides-Extra: sql
Provides-Extra: tests
Provides-Extra: xpack-llm
Provides-Extra: xpack-llm-docs
Provides-Extra: xpack-llm-local
Provides-Extra: xpack-sharepoint
License-File: LICENSE.txt
License-File: LICENSE_abomonation-LICENSE-MIT
License-File: LICENSE_adler2-LICENSE-0BSD
License-File: LICENSE_adler2-LICENSE-APACHE
License-File: LICENSE_adler2-LICENSE-MIT
License-File: LICENSE_adler32-LICENSE-ZLIB
License-File: LICENSE_ahash-LICENSE-APACHE
License-File: LICENSE_ahash-LICENSE-MIT
License-File: LICENSE_aho-corasick-LICENSE-MIT
License-File: LICENSE_airbyte_serverless-LICENSE-MIT
License-File: LICENSE_alloc-no-stdlib-LICENSE-BSD
License-File: LICENSE_alloc-stdlib-LICENSE-BSD
License-File: LICENSE_allocator-api2-LICENSE-APACHE
License-File: LICENSE_allocator-api2-LICENSE-MIT
License-File: LICENSE_anyhow-LICENSE-APACHE
License-File: LICENSE_anyhow-LICENSE-MIT
License-File: LICENSE_apache-avro-LICENSE-APACHE
License-File: LICENSE_arc-swap-LICENSE-APACHE
License-File: LICENSE_arc-swap-LICENSE-MIT
License-File: LICENSE_arcstr-LICENSE-APACHE
License-File: LICENSE_arcstr-LICENSE-MIT
License-File: LICENSE_arcstr-LICENSE-ZLIB
License-File: LICENSE_array-init-LICENSE-APACHE
License-File: LICENSE_array-init-LICENSE-MIT
License-File: LICENSE_arrayref-LICENSE-BSD
License-File: LICENSE_arrayvec-LICENSE-APACHE
License-File: LICENSE_arrayvec-LICENSE-MIT
License-File: LICENSE_arrow-LICENSE-APACHE
License-File: LICENSE_arrow-arith-LICENSE-APACHE
License-File: LICENSE_arrow-array-LICENSE-APACHE
License-File: LICENSE_arrow-buffer-LICENSE-APACHE
License-File: LICENSE_arrow-cast-LICENSE-APACHE
License-File: LICENSE_arrow-csv-LICENSE-APACHE
License-File: LICENSE_arrow-data-LICENSE-APACHE
License-File: LICENSE_arrow-ipc-LICENSE-APACHE
License-File: LICENSE_arrow-json-LICENSE-APACHE
License-File: LICENSE_arrow-ord-LICENSE-APACHE
License-File: LICENSE_arrow-row-LICENSE-APACHE
License-File: LICENSE_arrow-schema-LICENSE-APACHE
License-File: LICENSE_arrow-select-LICENSE-APACHE
License-File: LICENSE_arrow-string-LICENSE-APACHE
License-File: LICENSE_assert_matches-LICENSE-APACHE
License-File: LICENSE_assert_matches-LICENSE-MIT
License-File: LICENSE_async-compression-LICENSE-APACHE
License-File: LICENSE_async-compression-LICENSE-MIT
License-File: LICENSE_async-lock-LICENSE-APACHE
License-File: LICENSE_async-lock-LICENSE-MIT
License-File: LICENSE_async-nats-LICENSE-APACHE
License-File: LICENSE_async-stream-LICENSE-MIT
License-File: LICENSE_async-stream-impl-LICENSE-MIT
License-File: LICENSE_async-trait-LICENSE-APACHE
License-File: LICENSE_async-trait-LICENSE-MIT
License-File: LICENSE_atoi-LICENSE-MIT
License-File: LICENSE_atomic-waker-LICENSE-APACHE
License-File: LICENSE_atomic-waker-LICENSE-MIT
License-File: LICENSE_attohttpc-LICENSE
License-File: LICENSE_autocfg-LICENSE-APACHE
License-File: LICENSE_autocfg-LICENSE-MIT
License-File: LICENSE_aws-config-LICENSE-APACHE
License-File: LICENSE_aws-credential-types-LICENSE-APACHE
License-File: LICENSE_aws-creds-LICENSE-MIT
License-File: LICENSE_aws-region-LICENSE-MIT
License-File: LICENSE_aws-runtime-LICENSE-APACHE
License-File: LICENSE_aws-sdk-dynamodb-LICENSE-APACHE
License-File: LICENSE_aws-sdk-sso-LICENSE-APACHE
License-File: LICENSE_aws-sdk-ssooidc-LICENSE-APACHE
License-File: LICENSE_aws-sdk-sts-LICENSE-APACHE
License-File: LICENSE_aws-sigv4-LICENSE-APACHE
License-File: LICENSE_aws-smithy-async-LICENSE-APACHE
License-File: LICENSE_aws-smithy-http-LICENSE-APACHE
License-File: LICENSE_aws-smithy-json-LICENSE-APACHE
License-File: LICENSE_aws-smithy-query-LICENSE-APACHE
License-File: LICENSE_aws-smithy-runtime-LICENSE-APACHE
License-File: LICENSE_aws-smithy-runtime-api-LICENSE-APACHE
License-File: LICENSE_aws-smithy-types-LICENSE-APACHE
License-File: LICENSE_aws-smithy-xml-LICENSE-APACHE
License-File: LICENSE_aws-types-LICENSE-APACHE
License-File: LICENSE_axum-LICENSE-MIT
License-File: LICENSE_backon-LICENSE-APACHE
License-File: LICENSE_base32-LICENSE-APACHE
License-File: LICENSE_base32-LICENSE-MIT
License-File: LICENSE_base64-LICENSE-APACHE
License-File: LICENSE_base64-LICENSE-MIT
License-File: LICENSE_base64-simd-LICENSE-MIT
License-File: LICENSE_base64ct-LICENSE-APACHE
License-File: LICENSE_base64ct-LICENSE-MIT
License-File: LICENSE_bigdecimal-LICENSE-APACHE
License-File: LICENSE_bigdecimal-LICENSE-MIT
License-File: LICENSE_bimap-rs-LICENSE-MIT
License-File: LICENSE_bincode-LICENSE-MIT
License-File: LICENSE_bitflags-LICENSE-APACHE
License-File: LICENSE_bitflags-LICENSE-MIT
License-File: LICENSE_bitpacking-LICENSE-MIT
License-File: LICENSE_bitvec-LICENSE-MIT
License-File: LICENSE_blake3-LICENSE-APACHE
License-File: LICENSE_borsh-LICENSE-APACHE
License-File: LICENSE_borsh-LICENSE-MIT
License-File: LICENSE_borsh-derive-LICENSE-APACHE
License-File: LICENSE_brotli-decompressor-LICENSE-BSD
License-File: LICENSE_brotli-decompressor-LICENSE-MIT
License-File: LICENSE_bson-LICENSE-MIT
License-File: LICENSE_bytecheck-LICENSE-MIT
License-File: LICENSE_bytecheck_derive-LICENSE-MIT
License-File: LICENSE_bytemuck-LICENSE-APACHE
License-File: LICENSE_bytemuck-LICENSE-MIT
License-File: LICENSE_bytemuck-LICENSE-ZLIB
License-File: LICENSE_byteorder-LICENSE-MIT
License-File: LICENSE_bytes-LICENSE-MIT
License-File: LICENSE_bytes-utils-LICENSE-APACHE
License-File: LICENSE_bytes-utils-LICENSE-MIT
License-File: LICENSE_bzip2-LICENSE-APACHE
License-File: LICENSE_bzip2-LICENSE-MIT
License-File: LICENSE_bzip2-sys-LICENSE-APACHE
License-File: LICENSE_bzip2-sys-LICENSE-MIT
License-File: LICENSE_cached-LICENSE-MIT
License-File: LICENSE_cached_proc_macro-LICENSE-MIT
License-File: LICENSE_cached_proc_macro_types-LICENSE-MIT
License-File: LICENSE_cc-LICENSE-APACHE
License-File: LICENSE_cc-LICENSE-MIT
License-File: LICENSE_census-LICENSE-MIT
License-File: LICENSE_cfg-if-LICENSE-APACHE
License-File: LICENSE_cfg-if-LICENSE-MIT
License-File: LICENSE_cfg_aliases-LICENSE-MIT
License-File: LICENSE_chrono-LICENSE-APACHE
License-File: LICENSE_chrono-LICENSE-MIT
License-File: LICENSE_chrono-tz-LICENSE-APACHE
License-File: LICENSE_chrono-tz-LICENSE-MIT
License-File: LICENSE_chrono-tz-build-LICENSE-APACHE
License-File: LICENSE_chrono-tz-build-LICENSE-MIT
License-File: LICENSE_cmake-LICENSE-APACHE
License-File: LICENSE_cmake-LICENSE-MIT
License-File: LICENSE_codespan-reporting-LICENSE-APACHE
License-File: LICENSE_comfy-table-LICENSE-MIT
License-File: LICENSE_concurrent-queue-LICENSE-APACHE
License-File: LICENSE_concurrent-queue-LICENSE-MIT
License-File: LICENSE_const-oid-LICENSE-APACHE
License-File: LICENSE_const-oid-LICENSE-MIT
License-File: LICENSE_const-random-LICENSE-APACHE
License-File: LICENSE_const-random-LICENSE-MIT
License-File: LICENSE_const-random-macro-LICENSE-APACHE
License-File: LICENSE_const-random-macro-LICENSE-MIT
License-File: LICENSE_constant_time_eq-LICENSE-APACHE
License-File: LICENSE_constant_time_eq-LICENSE-MIT0
License-File: LICENSE_convert_case-LICENSE-MIT
License-File: LICENSE_core2-LICENSE-APACHE
License-File: LICENSE_core2-LICENSE-MIT
License-File: LICENSE_crc32fast-LICENSE-APACHE
License-File: LICENSE_crc32fast-LICENSE-MIT
License-File: LICENSE_crossbeam-channel-LICENSE-APACHE
License-File: LICENSE_crossbeam-channel-LICENSE-MIT
License-File: LICENSE_crossbeam-deque-LICENSE-APACHE
License-File: LICENSE_crossbeam-deque-LICENSE-MIT
License-File: LICENSE_crossbeam-epoch-LICENSE-APACHE
License-File: LICENSE_crossbeam-epoch-LICENSE-MIT
License-File: LICENSE_crossbeam-utils-LICENSE-APACHE
License-File: LICENSE_crossbeam-utils-LICENSE-MIT
License-File: LICENSE_csv-LICENSE-MIT
License-File: LICENSE_csv-core-LICENSE-MIT
License-File: LICENSE_curve25519-dalek-derive-LICENSE-APACHE
License-File: LICENSE_curve25519-dalek-derive-LICENSE-MIT
License-File: LICENSE_cxx-LICENSE-APACHE
License-File: LICENSE_cxx-LICENSE-MIT
License-File: LICENSE_cxx-build-LICENSE-APACHE
License-File: LICENSE_cxx-build-LICENSE-MIT
License-File: LICENSE_cxxbridge-flags-LICENSE-APACHE
License-File: LICENSE_cxxbridge-flags-LICENSE-MIT
License-File: LICENSE_cxxbridge-macro-LICENSE-APACHE
License-File: LICENSE_cxxbridge-macro-LICENSE-MIT
License-File: LICENSE_darling-LICENSE-MIT
License-File: LICENSE_darling_core-LICENSE-MIT
License-File: LICENSE_darling_macro-LICENSE-MIT
License-File: LICENSE_dary_heap-LICENSE-APACHE
License-File: LICENSE_dary_heap-LICENSE-MIT
License-File: LICENSE_dashmap-LICENSE-MIT
License-File: LICENSE_data-encoding-LICENSE-MIT
License-File: LICENSE_datafusion-LICENSE-APACHE
License-File: LICENSE_datafusion-catalog-LICENSE-APACHE
License-File: LICENSE_datafusion-common-LICENSE-APACHE
License-File: LICENSE_datafusion-common-runtime-LICENSE-APACHE
License-File: LICENSE_datafusion-doc-LICENSE-APACHE
License-File: LICENSE_datafusion-execution-LICENSE-APACHE
License-File: LICENSE_datafusion-expr-LICENSE-APACHE
License-File: LICENSE_datafusion-expr-common-LICENSE-APACHE
License-File: LICENSE_datafusion-functions-LICENSE-APACHE
License-File: LICENSE_datafusion-functions-aggregate-LICENSE-APACHE
License-File: LICENSE_datafusion-functions-aggregate-common-LICENSE-APACHE
License-File: LICENSE_datafusion-functions-nested-LICENSE-APACHE
License-File: LICENSE_datafusion-functions-table-LICENSE-APACHE
License-File: LICENSE_datafusion-functions-window-LICENSE-APACHE
License-File: LICENSE_datafusion-functions-window-common-LICENSE-APACHE
License-File: LICENSE_datafusion-macros-LICENSE-APACHE
License-File: LICENSE_datafusion-optimizer-LICENSE-APACHE
License-File: LICENSE_datafusion-physical-expr-LICENSE-APACHE
License-File: LICENSE_datafusion-physical-expr-common-LICENSE-APACHE
License-File: LICENSE_datafusion-physical-optimizer-LICENSE-APACHE
License-File: LICENSE_datafusion-physical-plan-LICENSE-APACHE
License-File: LICENSE_datafusion-proto-LICENSE-APACHE
License-File: LICENSE_datafusion-proto-common-LICENSE-APACHE
License-File: LICENSE_datafusion-sql-LICENSE-APACHE
License-File: LICENSE_delta_kernel-LICENSE-APACHE
License-File: LICENSE_delta_kernel_derive-LICENSE-APACHE
License-File: LICENSE_deltalake-LICENSE-APACHE
License-File: LICENSE_deltalake-aws-LICENSE-APACHE
License-File: LICENSE_deltalake-core-LICENSE-APACHE
License-File: LICENSE_der-LICENSE-APACHE
License-File: LICENSE_der-LICENSE-MIT
License-File: LICENSE_deranged-LICENSE-APACHE
License-File: LICENSE_deranged-LICENSE-MIT
License-File: LICENSE_derivative-LICENSE-APACHE
License-File: LICENSE_derivative-LICENSE-MIT
License-File: LICENSE_derive-syn-parse-LICENSE-APACHE
License-File: LICENSE_derive-syn-parse-LICENSE-MIT
License-File: LICENSE_derive-where-LICENSE-APACHE
License-File: LICENSE_derive-where-LICENSE-MIT
License-File: LICENSE_derive_builder-LICENSE-APACHE
License-File: LICENSE_derive_builder-LICENSE-MIT
License-File: LICENSE_derive_builder_core-LICENSE-APACHE
License-File: LICENSE_derive_builder_core-LICENSE-MIT
License-File: LICENSE_derive_builder_macro-LICENSE-APACHE
License-File: LICENSE_derive_builder_macro-LICENSE-MIT
License-File: LICENSE_derive_more-LICENSE-MIT
License-File: LICENSE_deunicode-LICENSE-BSD
License-File: LICENSE_differential-dataflow-LICENSE-MIT
License-File: LICENSE_displaydoc-LICENSE-APACHE
License-File: LICENSE_displaydoc-LICENSE-MIT
License-File: LICENSE_dlv-list-LICENSE-APACHE
License-File: LICENSE_dlv-list-LICENSE-MIT
License-File: LICENSE_downcast-LICENSE-MIT
License-File: LICENSE_downcast-rs-LICENSE-APACHE
License-File: LICENSE_downcast-rs-LICENSE-MIT
License-File: LICENSE_dtoa-LICENSE-APACHE
License-File: LICENSE_dtoa-LICENSE-MIT
License-File: LICENSE_dyn-clone-LICENSE-APACHE
License-File: LICENSE_dyn-clone-LICENSE-MIT
License-File: LICENSE_ed25519-LICENSE-APACHE
License-File: LICENSE_ed25519-LICENSE-MIT
License-File: LICENSE_either-LICENSE-APACHE
License-File: LICENSE_either-LICENSE-MIT
License-File: LICENSE_elasticsearch-LICENSE-APACHE
License-File: LICENSE_encoding_rs-LICENSE-APACHE
License-File: LICENSE_encoding_rs-LICENSE-MIT
License-File: LICENSE_encoding_rs-LICENSE-WHATWG
License-File: LICENSE_enum-as-inner-LICENSE-APACHE
License-File: LICENSE_enum-as-inner-LICENSE-MIT
License-File: LICENSE_equivalent-LICENSE-APACHE
License-File: LICENSE_equivalent-LICENSE-MIT
License-File: LICENSE_errno-LICENSE-APACHE
License-File: LICENSE_errno-LICENSE-MIT
License-File: LICENSE_event-listener-LICENSE-APACHE
License-File: LICENSE_event-listener-LICENSE-MIT
License-File: LICENSE_event-listener-strategy-LICENSE-APACHE
License-File: LICENSE_event-listener-strategy-LICENSE-MIT
License-File: LICENSE_eyre-LICENSE-APACHE
License-File: LICENSE_eyre-LICENSE-MIT
License-File: LICENSE_fallible-iterator-LICENSE-APACHE
License-File: LICENSE_fallible-iterator-LICENSE-MIT
License-File: LICENSE_fallible-streaming-iterator-LICENSE-APACHE
License-File: LICENSE_fallible-streaming-iterator-LICENSE-MIT
License-File: LICENSE_fastdivide-LICENSE-MIT
License-File: LICENSE_fastdivide-LICENSE-ZLIB
License-File: LICENSE_fastrand-LICENSE-APACHE
License-File: LICENSE_fastrand-LICENSE-MIT
License-File: LICENSE_fix-hidden-lifetime-bug-LICENSE-APACHE
License-File: LICENSE_fix-hidden-lifetime-bug-LICENSE-MIT
License-File: LICENSE_fix-hidden-lifetime-bug-LICENSE-ZLIB
License-File: LICENSE_fix-hidden-lifetime-bug-proc_macros-LICENSE-APACHE
License-File: LICENSE_fix-hidden-lifetime-bug-proc_macros-LICENSE-MIT
License-File: LICENSE_fix-hidden-lifetime-bug-proc_macros-LICENSE-ZLIB
License-File: LICENSE_fixedbitset-LICENSE-APACHE
License-File: LICENSE_fixedbitset-LICENSE-MIT
License-File: LICENSE_flagset-LICENSE-APACHE
License-File: LICENSE_flatbuffers-LICENSE-APACHE
License-File: LICENSE_flate2-LICENSE-APACHE
License-File: LICENSE_flate2-LICENSE-MIT
License-File: LICENSE_fnv-LICENSE-APACHE
License-File: LICENSE_fnv-LICENSE-MIT
License-File: LICENSE_foldhash-LICENSE-ZLIB
License-File: LICENSE_foreign-types-LICENSE-APACHE
License-File: LICENSE_foreign-types-LICENSE-MIT
License-File: LICENSE_foreign-types-shared-LICENSE-APACHE
License-File: LICENSE_foreign-types-shared-LICENSE-MIT
License-File: LICENSE_form_urlencoded-LICENSE-APACHE
License-File: LICENSE_form_urlencoded-LICENSE-MIT
License-File: LICENSE_fragile-LICENSE-APACHE
License-File: LICENSE_fs4-LICENSE-APACHE
License-File: LICENSE_fs4-LICENSE-MIT
License-File: LICENSE_funty-LICENSE-MIT
License-File: LICENSE_futures-LICENSE-APACHE
License-File: LICENSE_futures-LICENSE-MIT
License-File: LICENSE_futures-channel-LICENSE-APACHE
License-File: LICENSE_futures-channel-LICENSE-MIT
License-File: LICENSE_futures-core-LICENSE-APACHE
License-File: LICENSE_futures-core-LICENSE-MIT
License-File: LICENSE_futures-executor-LICENSE-APACHE
License-File: LICENSE_futures-executor-LICENSE-MIT
License-File: LICENSE_futures-io-LICENSE-APACHE
License-File: LICENSE_futures-io-LICENSE-MIT
License-File: LICENSE_futures-macro-LICENSE-APACHE
License-File: LICENSE_futures-macro-LICENSE-MIT
License-File: LICENSE_futures-sink-LICENSE-APACHE
License-File: LICENSE_futures-sink-LICENSE-MIT
License-File: LICENSE_futures-task-LICENSE-APACHE
License-File: LICENSE_futures-task-LICENSE-MIT
License-File: LICENSE_futures-util-LICENSE-APACHE
License-File: LICENSE_futures-util-LICENSE-MIT
License-File: LICENSE_generic-array-LICENSE-MIT
License-File: LICENSE_getopts-LICENSE-APACHE
License-File: LICENSE_getopts-LICENSE-MIT
License-File: LICENSE_getrandom-LICENSE-APACHE
License-File: LICENSE_getrandom-LICENSE-MIT
License-File: LICENSE_glob-LICENSE-APACHE
License-File: LICENSE_glob-LICENSE-MIT
License-File: LICENSE_h2-LICENSE-MIT
License-File: LICENSE_half-LICENSE-APACHE
License-File: LICENSE_half-LICENSE-MIT
License-File: LICENSE_hashbrown-LICENSE-APACHE
License-File: LICENSE_hashbrown-LICENSE-MIT
License-File: LICENSE_hashlink-LICENSE-APACHE
License-File: LICENSE_hashlink-LICENSE-MIT
License-File: LICENSE_heck-LICENSE-APACHE
License-File: LICENSE_heck-LICENSE-MIT
License-File: LICENSE_hex-LICENSE-APACHE
License-File: LICENSE_hex-LICENSE-MIT
License-File: LICENSE_hickory-proto-LICENSE-APACHE
License-File: LICENSE_hickory-proto-LICENSE-MIT
License-File: LICENSE_hickory-resolver-LICENSE-APACHE
License-File: LICENSE_hickory-resolver-LICENSE-MIT
License-File: LICENSE_home-LICENSE-APACHE
License-File: LICENSE_home-LICENSE-MIT
License-File: LICENSE_hostname-LICENSE-MIT
License-File: LICENSE_http-LICENSE-APACHE
License-File: LICENSE_http-LICENSE-MIT
License-File: LICENSE_http-body-LICENSE-MIT
License-File: LICENSE_http-body-util-LICENSE-MIT
License-File: LICENSE_httparse-LICENSE-APACHE
License-File: LICENSE_httparse-LICENSE-MIT
License-File: LICENSE_httpdate-LICENSE-APACHE
License-File: LICENSE_httpdate-LICENSE-MIT
License-File: LICENSE_humantime-LICENSE-APACHE
License-File: LICENSE_humantime-LICENSE-MIT
License-File: LICENSE_hyper-LICENSE-MIT
License-File: LICENSE_hyper-rustls-LICENSE-APACHE
License-File: LICENSE_hyper-rustls-LICENSE-ISC
License-File: LICENSE_hyper-rustls-LICENSE-MIT
License-File: LICENSE_hyper-timeout-LICENSE-APACHE
License-File: LICENSE_hyper-timeout-LICENSE-MIT
License-File: LICENSE_hyper-tls-LICENSE-APACHE
License-File: LICENSE_hyper-tls-LICENSE-MIT
License-File: LICENSE_hyper-util-LICENSE-MIT
License-File: LICENSE_iana-time-zone-LICENSE-APACHE
License-File: LICENSE_iana-time-zone-LICENSE-MIT
License-File: LICENSE_iceberg-LICENSE-APACHE
License-File: LICENSE_iceberg-catalog-rest-LICENSE-APACHE
License-File: LICENSE_icu-LICENSE-UNICODE
License-File: LICENSE_id-arena-LICENSE-APACHE
License-File: LICENSE_id-arena-LICENSE-MIT
License-File: LICENSE_ident_case-LICENSE-APACHE
License-File: LICENSE_ident_case-LICENSE-MIT
License-File: LICENSE_idna-LICENSE-APACHE
License-File: LICENSE_idna-LICENSE-MIT
License-File: LICENSE_idna_adapter-LICENSE-APACHE
License-File: LICENSE_idna_adapter-LICENSE-MIT
License-File: LICENSE_indenter-LICENSE-APACHE
License-File: LICENSE_indenter-LICENSE-MIT
License-File: LICENSE_indexmap-LICENSE-APACHE
License-File: LICENSE_indexmap-LICENSE-MIT
License-File: LICENSE_indoc-LICENSE-APACHE
License-File: LICENSE_indoc-LICENSE-MIT
License-File: LICENSE_instant-LICENSE-BSD
License-File: LICENSE_integer-encoding-LICENSE-MIT
License-File: LICENSE_inventory-LICENSE-APACHE
License-File: LICENSE_inventory-LICENSE-MIT
License-File: LICENSE_ipnet-LICENSE-APACHE
License-File: LICENSE_ipnet-LICENSE-MIT
License-File: LICENSE_itertools-LICENSE-APACHE
License-File: LICENSE_itertools-LICENSE-MIT
License-File: LICENSE_itoa-LICENSE-APACHE
License-File: LICENSE_itoa-LICENSE-MIT
License-File: LICENSE_jemalloc-sys-LICENSE-APACHE
License-File: LICENSE_jemalloc-sys-LICENSE-MIT
License-File: LICENSE_jemallocator-LICENSE-APACHE
License-File: LICENSE_jemallocator-LICENSE-MIT
License-File: LICENSE_jmespath-LICENSE-MIT
License-File: LICENSE_jobserver-LICENSE-APACHE
License-File: LICENSE_jobserver-LICENSE-MIT
License-File: LICENSE_lazy_static-LICENSE-APACHE
License-File: LICENSE_lazy_static-LICENSE-MIT
License-File: LICENSE_levenshtein_automata-LICENSE-MIT
License-File: LICENSE_lexical-core-LICENSE-APACHE
License-File: LICENSE_lexical-core-LICENSE-MIT
License-File: LICENSE_lexical-parse-float-LICENSE-APACHE
License-File: LICENSE_lexical-parse-float-LICENSE-MIT
License-File: LICENSE_lexical-parse-integer-LICENSE-APACHE
License-File: LICENSE_lexical-parse-integer-LICENSE-MIT
License-File: LICENSE_lexical-util-LICENSE-APACHE
License-File: LICENSE_lexical-util-LICENSE-MIT
License-File: LICENSE_lexical-write-float-LICENSE-APACHE
License-File: LICENSE_lexical-write-float-LICENSE-MIT
License-File: LICENSE_lexical-write-integer-LICENSE-APACHE
License-File: LICENSE_lexical-write-integer-LICENSE-MIT
License-File: LICENSE_libc-LICENSE-APACHE
License-File: LICENSE_libc-LICENSE-MIT
License-File: LICENSE_libflate-LICENSE-MIT
License-File: LICENSE_libflate_lz77-LICENSE-MIT
License-File: LICENSE_libm-LICENSE
License-File: LICENSE_libm-LICENSE-APACHE
License-File: LICENSE_libsqlite3-sys-LICENSE-MIT
License-File: LICENSE_libz-sys-LICENSE-APACHE
License-File: LICENSE_libz-sys-LICENSE-MIT
License-File: LICENSE_link-cplusplus-LICENSE-APACHE
License-File: LICENSE_link-cplusplus-LICENSE-MIT
License-File: LICENSE_linked-hash-map-LICENSE-APACHE
License-File: LICENSE_linked-hash-map-LICENSE-MIT
License-File: LICENSE_linux-raw-sys-LICENSE-APACHE
License-File: LICENSE_linux-raw-sys-LICENSE-MIT
License-File: LICENSE_lock_api-LICENSE-APACHE
License-File: LICENSE_lock_api-LICENSE-MIT
License-File: LICENSE_log-LICENSE-APACHE
License-File: LICENSE_log-LICENSE-MIT
License-File: LICENSE_lru-LICENSE-MIT
License-File: LICENSE_lru-cache-LICENSE-APACHE
License-File: LICENSE_lru-cache-LICENSE-MIT
License-File: LICENSE_lz4_flex-LICENSE-MIT
License-File: LICENSE_lzma-sys-LICENSE-APACHE
License-File: LICENSE_lzma-sys-LICENSE-MIT
License-File: LICENSE_macro_magic-LICENSE-MIT
License-File: LICENSE_macro_magic_core-LICENSE-MIT
License-File: LICENSE_macro_magic_core_macros-LICENSE-MIT
License-File: LICENSE_macro_magic_macros-LICENSE-MIT
License-File: LICENSE_maplit-LICENSE-APACHE
License-File: LICENSE_maplit-LICENSE-MIT
License-File: LICENSE_match_cfg-LICENSE-APACHE
License-File: LICENSE_match_cfg-LICENSE-MIT
License-File: LICENSE_matchit-LICENSE-MIT
License-File: LICENSE_matrixmultiply-LICENSE-APACHE
License-File: LICENSE_matrixmultiply-LICENSE-MIT
License-File: LICENSE_maybe-async-LICENSE-MIT
License-File: LICENSE_md5-LICENSE-APACHE
License-File: LICENSE_md5-LICENSE-MIT
License-File: LICENSE_measure_time-LICENSE-MIT
License-File: LICENSE_memchr-LICENSE-MIT
License-File: LICENSE_memmap2-LICENSE-APACHE
License-File: LICENSE_memmap2-LICENSE-MIT
License-File: LICENSE_memoffset-LICENSE-MIT
License-File: LICENSE_mime-LICENSE-APACHE
License-File: LICENSE_mime-LICENSE-MIT
License-File: LICENSE_minimal-lexical-LICENSE-APACHE
License-File: LICENSE_minimal-lexical-LICENSE-MIT
License-File: LICENSE_miniz_oxide-LICENSE-APACHE
License-File: LICENSE_miniz_oxide-LICENSE-MIT
License-File: LICENSE_miniz_oxide-LICENSE-ZLIB
License-File: LICENSE_mio-LICENSE-MIT
License-File: LICENSE_mockall-LICENSE-APACHE
License-File: LICENSE_mockall-LICENSE-MIT
License-File: LICENSE_mockall_derive-LICENSE-APACHE
License-File: LICENSE_mockall_derive-LICENSE-MIT
License-File: LICENSE_moka-LICENSE-APACHE
License-File: LICENSE_moka-LICENSE-MIT
License-File: LICENSE_mongodb-LICENSE-APACHE
License-File: LICENSE_murmur3-LICENSE-APACHE
License-File: LICENSE_murmur3-LICENSE-MIT
License-File: LICENSE_murmurhash32-LICENSE-MIT
License-File: LICENSE_native-tls-LICENSE-APACHE
License-File: LICENSE_native-tls-LICENSE-MIT
License-File: LICENSE_ndarray-LICENSE-APACHE
License-File: LICENSE_ndarray-LICENSE-MIT
License-File: LICENSE_nix-LICENSE-MIT
License-File: LICENSE_nkeys-LICENSE-APACHE
License-File: LICENSE_nom-LICENSE-MIT
License-File: LICENSE_nuid-LICENSE-APACHE
License-File: LICENSE_num-LICENSE-APACHE
License-File: LICENSE_num-LICENSE-MIT
License-File: LICENSE_num-bigint-LICENSE-APACHE
License-File: LICENSE_num-bigint-LICENSE-MIT
License-File: LICENSE_num-complex-LICENSE-APACHE
License-File: LICENSE_num-complex-LICENSE-MIT
License-File: LICENSE_num-conv-LICENSE-APACHE
License-File: LICENSE_num-conv-LICENSE-MIT
License-File: LICENSE_num-integer-LICENSE-APACHE
License-File: LICENSE_num-integer-LICENSE-MIT
License-File: LICENSE_num-iter-LICENSE-APACHE
License-File: LICENSE_num-iter-LICENSE-MIT
License-File: LICENSE_num-rational-LICENSE-APACHE
License-File: LICENSE_num-rational-LICENSE-MIT
License-File: LICENSE_num-traits-LICENSE-APACHE
License-File: LICENSE_num-traits-LICENSE-MIT
License-File: LICENSE_num_cpus-LICENSE-APACHE
License-File: LICENSE_num_cpus-LICENSE-MIT
License-File: LICENSE_num_enum-LICENSE-APACHE
License-File: LICENSE_num_enum-LICENSE-BSD
License-File: LICENSE_num_enum-LICENSE-MIT
License-File: LICENSE_num_enum_derive-LICENSE-APACHE
License-File: LICENSE_num_enum_derive-LICENSE-BSD
License-File: LICENSE_num_enum_derive-LICENSE-MIT
License-File: LICENSE_numpy-LICENSE-BSD
License-File: LICENSE_object-store-LICENSE-APACHE
License-File: LICENSE_once_cell-LICENSE-APACHE
License-File: LICENSE_once_cell-LICENSE-MIT
License-File: LICENSE_oneshot-LICENSE-APACHE
License-File: LICENSE_oneshot-LICENSE-MIT
License-File: LICENSE_opendal-LICENSE-APACHE
License-File: LICENSE_openssl-probe-LICENSE-APACHE
License-File: LICENSE_openssl-probe-LICENSE-MIT
License-File: LICENSE_openssl-src-LICENSE-APACHE
License-File: LICENSE_openssl-src-LICENSE-MIT
License-File: LICENSE_opentelemetry-LICENSE-APACHE
License-File: LICENSE_opentelemetry-otlp-LICENSE-APACHE
License-File: LICENSE_opentelemetry-proto-LICENSE-APACHE
License-File: LICENSE_opentelemetry-semantic-conventions-LICENSE-APACHE
License-File: LICENSE_opentelemetry_sdk-LICENSE-APACHE
License-File: LICENSE_ordered-float-LICENSE-MIT
License-File: LICENSE_ordered-multimap-LICENSE-MIT
License-File: LICENSE_outref-LICENSE-MIT
License-File: LICENSE_ownedbytes-LICENSE-MIT
License-File: LICENSE_parking-LICENSE-APACHE
License-File: LICENSE_parking-LICENSE-MIT
License-File: LICENSE_parking_lot-LICENSE-APACHE
License-File: LICENSE_parking_lot-LICENSE-MIT
License-File: LICENSE_parking_lot_core-LICENSE-APACHE
License-File: LICENSE_parking_lot_core-LICENSE-MIT
License-File: LICENSE_parquet-LICENSE-APACHE
License-File: LICENSE_parse-zoneinfo-LICENSE-MIT
License-File: LICENSE_paste-LICENSE-APACHE
License-File: LICENSE_paste-LICENSE-MIT
License-File: LICENSE_pbkdf2-LICENSE-APACHE
License-File: LICENSE_pbkdf2-LICENSE-MIT
License-File: LICENSE_pem-rfc7468-LICENSE-APACHE
License-File: LICENSE_pem-rfc7468-LICENSE-MIT
License-File: LICENSE_percent-encoding-LICENSE-APACHE
License-File: LICENSE_percent-encoding-LICENSE-MIT
License-File: LICENSE_petgraph-LICENSE-APACHE
License-File: LICENSE_petgraph-LICENSE-MIT
License-File: LICENSE_phf-LICENSE-MIT
License-File: LICENSE_phf_codegen-LICENSE-MIT
License-File: LICENSE_phf_generator-LICENSE-MIT
License-File: LICENSE_phf_shared-LICENSE-MIT
License-File: LICENSE_pin-project-LICENSE-APACHE
License-File: LICENSE_pin-project-LICENSE-MIT
License-File: LICENSE_pin-project-internal-LICENSE-APACHE
License-File: LICENSE_pin-project-internal-LICENSE-MIT
License-File: LICENSE_pin-project-lite-LICENSE-APACHE
License-File: LICENSE_pin-project-lite-LICENSE-MIT
License-File: LICENSE_pin-utils-LICENSE-APACHE
License-File: LICENSE_pin-utils-LICENSE-MIT
License-File: LICENSE_pkcs8-LICENSE-APACHE
License-File: LICENSE_pkcs8-LICENSE-MIT
License-File: LICENSE_pkg-config-LICENSE-APACHE
License-File: LICENSE_pkg-config-LICENSE-MIT
License-File: LICENSE_portable-atomic-LICENSE-APACHE
License-File: LICENSE_portable-atomic-LICENSE-MIT
License-File: LICENSE_postgres-LICENSE-APACHE
License-File: LICENSE_postgres-LICENSE-MIT
License-File: LICENSE_postgres-protocol-LICENSE-APACHE
License-File: LICENSE_postgres-protocol-LICENSE-MIT
License-File: LICENSE_postgres-types-LICENSE-APACHE
License-File: LICENSE_postgres-types-LICENSE-MIT
License-File: LICENSE_powerfmt-LICENSE-APACHE
License-File: LICENSE_powerfmt-LICENSE-MIT
License-File: LICENSE_ppv-lite86-LICENSE-APACHE
License-File: LICENSE_ppv-lite86-LICENSE-MIT
License-File: LICENSE_predicates-LICENSE-APACHE
License-File: LICENSE_predicates-LICENSE-MIT
License-File: LICENSE_predicates-core-LICENSE-APACHE
License-File: LICENSE_predicates-core-LICENSE-MIT
License-File: LICENSE_predicates-tree-LICENSE-APACHE
License-File: LICENSE_predicates-tree-LICENSE-MIT
License-File: LICENSE_proc-macro-crate-LICENSE-APACHE
License-File: LICENSE_proc-macro-crate-LICENSE-MIT
License-File: LICENSE_proc-macro2-LICENSE-APACHE
License-File: LICENSE_proc-macro2-LICENSE-MIT
License-File: LICENSE_prometheus-client-LICENSE-APACHE
License-File: LICENSE_prometheus-client-LICENSE-MIT
License-File: LICENSE_prometheus-client-derive-encode-LICENSE-APACHE
License-File: LICENSE_prometheus-client-derive-encode-LICENSE-MIT
License-File: LICENSE_prost-LICENSE-APACHE
License-File: LICENSE_prost-derive-LICENSE-APACHE
License-File: LICENSE_psm-LICENSE-APACHE
License-File: LICENSE_psm-LICENSE-MIT
License-File: LICENSE_ptr_meta-LICENSE-MIT
License-File: LICENSE_ptr_meta_derive-LICENSE-MIT
License-File: LICENSE_pyo3-LICENSE-APACHE
License-File: LICENSE_pyo3-LICENSE-MIT
License-File: LICENSE_pyo3-asyncio-0-21-LICENSE-APACHE
License-File: LICENSE_pyo3-build-config-LICENSE-APACHE
License-File: LICENSE_pyo3-build-config-LICENSE-MIT
License-File: LICENSE_pyo3-ffi-LICENSE-APACHE
License-File: LICENSE_pyo3-ffi-LICENSE-MIT
License-File: LICENSE_pyo3-log-LICENSE-APACHE
License-File: LICENSE_pyo3-log-LICENSE-MIT
License-File: LICENSE_pyo3-macros-LICENSE-APACHE
License-File: LICENSE_pyo3-macros-LICENSE-MIT
License-File: LICENSE_pyo3-macros-backend-LICENSE-APACHE
License-File: LICENSE_pyo3-macros-backend-LICENSE-MIT
License-File: LICENSE_quick-xml-LICENSE-MIT
License-File: LICENSE_quinn-LICENSE-APACHE
License-File: LICENSE_quinn-LICENSE-MIT
License-File: LICENSE_quinn-proto-LICENSE-APACHE
License-File: LICENSE_quinn-proto-LICENSE-MIT
License-File: LICENSE_quinn-udp-LICENSE-APACHE
License-File: LICENSE_quinn-udp-LICENSE-MIT
License-File: LICENSE_quote-LICENSE-APACHE
License-File: LICENSE_quote-LICENSE-MIT
License-File: LICENSE_radium-LICENSE-MIT
License-File: LICENSE_rand-LICENSE-APACHE
License-File: LICENSE_rand-LICENSE-MIT
License-File: LICENSE_rand_chacha-LICENSE-APACHE
License-File: LICENSE_rand_chacha-LICENSE-MIT
License-File: LICENSE_rand_core-LICENSE-APACHE
License-File: LICENSE_rand_core-LICENSE-MIT
License-File: LICENSE_rand_distr-LICENSE-APACHE
License-File: LICENSE_rand_distr-LICENSE-MIT
License-File: LICENSE_rawpointer-LICENSE-APACHE
License-File: LICENSE_rawpointer-LICENSE-MIT
License-File: LICENSE_rayon-LICENSE-APACHE
License-File: LICENSE_rayon-LICENSE-MIT
License-File: LICENSE_rayon-core-LICENSE-APACHE
License-File: LICENSE_rayon-core-LICENSE-MIT
License-File: LICENSE_rdkafka-LICENSE-MIT
License-File: LICENSE_rdkafka-sys-LICENSE-MIT
License-File: LICENSE_recursive-LICENSE-MIT
License-File: LICENSE_recursive-proc-macro-impl-LICENSE-MIT
License-File: LICENSE_regex-LICENSE-APACHE
License-File: LICENSE_regex-LICENSE-MIT
License-File: LICENSE_regex-automata-LICENSE-APACHE
License-File: LICENSE_regex-automata-LICENSE-MIT
License-File: LICENSE_regex-lite-LICENSE-APACHE
License-File: LICENSE_regex-lite-LICENSE-MIT
License-File: LICENSE_regex-syntax-LICENSE-APACHE
License-File: LICENSE_regex-syntax-LICENSE-MIT
License-File: LICENSE_rend-LICENSE-MIT
License-File: LICENSE_reqsign-LICENSE-APACHE
License-File: LICENSE_reqwest-LICENSE-APACHE
License-File: LICENSE_reqwest-LICENSE-MIT
License-File: LICENSE_ring-LICENSE
License-File: LICENSE_rkyv-LICENSE-MIT
License-File: LICENSE_rkyv_derive-LICENSE-MIT
License-File: LICENSE_rle-decode-fast-LICENSE-APACHE
License-File: LICENSE_rle-decode-fast-LICENSE-MIT
License-File: LICENSE_roaring-LICENSE-APACHE
License-File: LICENSE_roaring-LICENSE-MIT
License-File: LICENSE_rusqlite-LICENSE-MIT
License-File: LICENSE_rust-ini-LICENSE-MIT
License-File: LICENSE_rust-s3-LICENSE-MIT
License-File: LICENSE_rust-stemmers-LICENSE-BSD
License-File: LICENSE_rust-stemmers-LICENSE-MIT
License-File: LICENSE_rust_decimal-LICENSE-MIT
License-File: LICENSE_rustc-hash-LICENSE-APACHE
License-File: LICENSE_rustc-hash-LICENSE-MIT
License-File: LICENSE_rustc_version-LICENSE-APACHE
License-File: LICENSE_rustc_version-LICENSE-MIT
License-File: LICENSE_rustc_version_runtime-LICENSE-MIT
License-File: LICENSE_rustix-LICENSE-APACHE
License-File: LICENSE_rustix-LICENSE-MIT
License-File: LICENSE_rustls-LICENSE-APACHE
License-File: LICENSE_rustls-LICENSE-ISC
License-File: LICENSE_rustls-LICENSE-MIT
License-File: LICENSE_rustls-native-certs-LICENSE-APACHE
License-File: LICENSE_rustls-native-certs-LICENSE-ISC
License-File: LICENSE_rustls-native-certs-LICENSE-MIT
License-File: LICENSE_rustls-pemfile-LICENSE-APACHE
License-File: LICENSE_rustls-pemfile-LICENSE-ISC
License-File: LICENSE_rustls-pemfile-LICENSE-MIT
License-File: LICENSE_rustls-pki-types-LICENSE-APACHE
License-File: LICENSE_rustls-pki-types-LICENSE-MIT
License-File: LICENSE_rustls-webpki-LICENSE-ISC
License-File: LICENSE_rustversion-LICENSE-APACHE
License-File: LICENSE_rustversion-LICENSE-MIT
License-File: LICENSE_ryu-LICENSE-APACHE
License-File: LICENSE_ryu-LICENSE-BOOST
License-File: LICENSE_same-file-LICENSE-MIT
License-File: LICENSE_scopeguard-LICENSE-APACHE
License-File: LICENSE_scopeguard-LICENSE-MIT
License-File: LICENSE_scratch-LICENSE-APACHE
License-File: LICENSE_scratch-LICENSE-MIT
License-File: LICENSE_sct-LICENSE-APACHE
License-File: LICENSE_sct-LICENSE-ISC
License-File: LICENSE_sct-LICENSE-MIT
License-File: LICENSE_seahash-LICENSE-MIT
License-File: LICENSE_semver-LICENSE-APACHE
License-File: LICENSE_semver-LICENSE-MIT
License-File: LICENSE_send_wrapper-LICENSE-APACHE
License-File: LICENSE_send_wrapper-LICENSE-MIT
License-File: LICENSE_seq-macro-LICENSE-APACHE
License-File: LICENSE_seq-macro-LICENSE-MIT
License-File: LICENSE_serde-LICENSE-APACHE
License-File: LICENSE_serde-LICENSE-MIT
License-File: LICENSE_serde_bytes-LICENSE-APACHE
License-File: LICENSE_serde_bytes-LICENSE-MIT
License-File: LICENSE_serde_derive-LICENSE-APACHE
License-File: LICENSE_serde_derive-LICENSE-MIT
License-File: LICENSE_serde_json-LICENSE-APACHE
License-File: LICENSE_serde_json-LICENSE-MIT
License-File: LICENSE_serde_nanos-LICENSE-APACHE
License-File: LICENSE_serde_nanos-LICENSE-MIT
License-File: LICENSE_serde_repr-LICENSE-APACHE
License-File: LICENSE_serde_repr-LICENSE-MIT
License-File: LICENSE_serde_urlencoded-LICENSE-APACHE
License-File: LICENSE_serde_urlencoded-LICENSE-MIT
License-File: LICENSE_serde_with-LICENSE-APACHE
License-File: LICENSE_serde_with-LICENSE-MIT
License-File: LICENSE_serde_with_macros-LICENSE-APACHE
License-File: LICENSE_serde_with_macros-LICENSE-MIT
License-File: LICENSE_shlex-LICENSE-APACHE
License-File: LICENSE_shlex-LICENSE-MIT
License-File: LICENSE_signal-hook-registry-LICENSE-APACHE
License-File: LICENSE_signal-hook-registry-LICENSE-MIT
License-File: LICENSE_signatory-LICENSE-APACHE
License-File: LICENSE_signatory-LICENSE-MIT
License-File: LICENSE_signature-LICENSE-APACHE
License-File: LICENSE_signature-LICENSE-MIT
License-File: LICENSE_simdutf8-LICENSE-APACHE
License-File: LICENSE_simdutf8-LICENSE-MIT
License-File: LICENSE_sketches-ddsketch-LICENSE-APACHE
License-File: LICENSE_slab-LICENSE-MIT
License-File: LICENSE_slug-LICENSE-APACHE
License-File: LICENSE_slug-LICENSE-MIT
License-File: LICENSE_smallvec-LICENSE-APACHE
License-File: LICENSE_smallvec-LICENSE-MIT
License-File: LICENSE_snafu-LICENSE-APACHE
License-File: LICENSE_snafu-LICENSE-MIT
License-File: LICENSE_snafu-derive-LICENSE-APACHE
License-File: LICENSE_snafu-derive-LICENSE-MIT
License-File: LICENSE_snap-BSD-LICENSE
License-File: LICENSE_socket2-LICENSE-APACHE
License-File: LICENSE_socket2-LICENSE-MIT
License-File: LICENSE_spin-LICENSE-MIT
License-File: LICENSE_spki-LICENSE-APACHE
License-File: LICENSE_spki-LICENSE-MIT
License-File: LICENSE_sqlparser-LICENSE-APACHE
License-File: LICENSE_stable_deref_trait-LICENSE-APACHE
License-File: LICENSE_stable_deref_trait-LICENSE-MIT
License-File: LICENSE_stacker-LICENSE-APACHE
License-File: LICENSE_stacker-LICENSE-MIT
License-File: LICENSE_static_assertions-LICENSE-APACHE
License-File: LICENSE_static_assertions-LICENSE-MIT
License-File: LICENSE_stringprep-LICENSE-APACHE
License-File: LICENSE_stringprep-LICENSE-MIT
License-File: LICENSE_strsim-LICENSE-MIT
License-File: LICENSE_strum-LICENSE-MIT
License-File: LICENSE_strum_macros-LICENSE-MIT
License-File: LICENSE_subtle-LICENSE-BSD
License-File: LICENSE_syn-LICENSE-APACHE
License-File: LICENSE_syn-LICENSE-MIT
License-File: LICENSE_sync_wrapper-LICENSE-APACHE
License-File: LICENSE_synstructure-LICENSE-MIT
License-File: LICENSE_sysinfo-LICENSE-MIT
License-File: LICENSE_tagptr-LICENSE-APACHE
License-File: LICENSE_tagptr-LICENSE-MIT
License-File: LICENSE_take_mut-LICENSE-MIT
License-File: LICENSE_tantivy-LICENSE-MIT
License-File: LICENSE_tantivy-bitpacker-LICENSE-MIT
License-File: LICENSE_tantivy-columnar-LICENSE-MIT
License-File: LICENSE_tantivy-common-LICENSE-MIT
License-File: LICENSE_tantivy-fst-LICENSE-MIT
License-File: LICENSE_tantivy-query-grammar-LICENSE-MIT
License-File: LICENSE_tantivy-sstable-LICENSE-MIT
License-File: LICENSE_tantivy-stacker-LICENSE-MIT
License-File: LICENSE_tantivy-tokenizer-api-LICENSE-MIT
License-File: LICENSE_tap-LICENSE-MIT
License-File: LICENSE_target-lexicon-LICENSE-APACHE
License-File: LICENSE_tempfile-LICENSE-APACHE
License-File: LICENSE_tempfile-LICENSE-MIT
License-File: LICENSE_termcolor-LICENSE-MIT
License-File: LICENSE_termtree-LICENSE-MIT
License-File: LICENSE_thiserror-LICENSE-APACHE
License-File: LICENSE_thiserror-LICENSE-MIT
License-File: LICENSE_thiserror-impl-LICENSE-APACHE
License-File: LICENSE_thiserror-impl-LICENSE-MIT
License-File: LICENSE_thrift-LICENSE-APACHE
License-File: LICENSE_time-LICENSE-APACHE
License-File: LICENSE_time-LICENSE-MIT
License-File: LICENSE_time-core-LICENSE-APACHE
License-File: LICENSE_time-core-LICENSE-MIT
License-File: LICENSE_time-macros-LICENSE-APACHE
License-File: LICENSE_time-macros-LICENSE-MIT
License-File: LICENSE_timely-LICENSE-MIT
License-File: LICENSE_timely_bytes-LICENSE-MIT
License-File: LICENSE_timely_communication-LICENSE-MIT
License-File: LICENSE_timely_logging-LICENSE-MIT
License-File: LICENSE_tinyvec-LICENSE-APACHE
License-File: LICENSE_tinyvec-LICENSE-MIT
License-File: LICENSE_tinyvec-LICENSE-ZLIB
License-File: LICENSE_tinyvec_macros-LICENSE-APACHE
License-File: LICENSE_tinyvec_macros-LICENSE-MIT
License-File: LICENSE_tinyvec_macros-LICENSE-ZLIB
License-File: LICENSE_tokio-LICENSE-MIT
License-File: LICENSE_tokio-macros-LICENSE-MIT
License-File: LICENSE_tokio-native-tls-LICENSE-MIT
License-File: LICENSE_tokio-postgres-LICENSE-APACHE
License-File: LICENSE_tokio-postgres-LICENSE-MIT
License-File: LICENSE_tokio-rustls-LICENSE-APACHE
License-File: LICENSE_tokio-rustls-LICENSE-MIT
License-File: LICENSE_tokio-stream-LICENSE-MIT
License-File: LICENSE_tokio-util-LICENSE-MIT
License-File: LICENSE_tokio-websockets-LICENSE-MIT
License-File: LICENSE_toml_datetime-LICENSE-APACHE
License-File: LICENSE_toml_datetime-LICENSE-MIT
License-File: LICENSE_toml_edit-LICENSE-APACHE
License-File: LICENSE_toml_edit-LICENSE-MIT
License-File: LICENSE_tonic-LICENSE-MIT
License-File: LICENSE_tower-LICENSE-MIT
License-File: LICENSE_tower-layer-LICENSE-MIT
License-File: LICENSE_tower-service-LICENSE-MIT
License-File: LICENSE_tracing-LICENSE-MIT
License-File: LICENSE_tracing-attributes-LICENSE-MIT
License-File: LICENSE_tracing-core-LICENSE-MIT
License-File: LICENSE_trim-in-place-LICENSE-MIT
License-File: LICENSE_try-lock-LICENSE-MIT
License-File: LICENSE_tryhard-LICENSE-APACHE
License-File: LICENSE_tryhard-LICENSE-MIT
License-File: LICENSE_twox-hash-LICENSE-MIT
License-File: LICENSE_typed-builder-LICENSE-APACHE
License-File: LICENSE_typed-builder-LICENSE-MIT
License-File: LICENSE_typed-builder-macro-LICENSE-APACHE
License-File: LICENSE_typed-builder-macro-LICENSE-MIT
License-File: LICENSE_typenum-LICENSE-APACHE
License-File: LICENSE_typenum-LICENSE-MIT
License-File: LICENSE_unicode-bidi-LICENSE-APACHE
License-File: LICENSE_unicode-bidi-LICENSE-MIT
License-File: LICENSE_unicode-ident-LICENSE-APACHE
License-File: LICENSE_unicode-ident-LICENSE-MIT
License-File: LICENSE_unicode-ident-LICENSE-UNICODE
License-File: LICENSE_unicode-normalization-LICENSE-APACHE
License-File: LICENSE_unicode-normalization-LICENSE-MIT
License-File: LICENSE_unicode-properties-LICENSE-APACHE
License-File: LICENSE_unicode-properties-LICENSE-MIT
License-File: LICENSE_unicode-segmentation-LICENSE-APACHE
License-File: LICENSE_unicode-segmentation-LICENSE-MIT
License-File: LICENSE_unicode-width-LICENSE-APACHE
License-File: LICENSE_unicode-width-LICENSE-MIT
License-File: LICENSE_unicode-xid-LICENSE-APACHE
License-File: LICENSE_unicode-xid-LICENSE-MIT
License-File: LICENSE_unindent-LICENSE-APACHE
License-File: LICENSE_unindent-LICENSE-MIT
License-File: LICENSE_untrusted-LICENSE-ISC
License-File: LICENSE_url-LICENSE-APACHE
License-File: LICENSE_url-LICENSE-MIT
License-File: LICENSE_urlencoding-LICENSE-MIT
License-File: LICENSE_usearch-LICENSE-APACHE
License-File: LICENSE_utf16_iter-LICENSE-APACHE
License-File: LICENSE_utf16_iter-LICENSE-MIT
License-File: LICENSE_utf8-ranges-LICENSE-MIT
License-File: LICENSE_utf8_iter-LICENSE-APACHE
License-File: LICENSE_utf8_iter-LICENSE-MIT
License-File: LICENSE_uuid-LICENSE-APACHE
License-File: LICENSE_uuid-LICENSE-MIT
License-File: LICENSE_vcpkg-LICENSE-APACHE
License-File: LICENSE_vcpkg-LICENSE-MIT
License-File: LICENSE_version_check-LICENSE-APACHE
License-File: LICENSE_version_check-LICENSE-MIT
License-File: LICENSE_visibility-LICENSE-APACHE
License-File: LICENSE_visibility-LICENSE-MIT
License-File: LICENSE_visibility-LICENSE-ZLIB
License-File: LICENSE_void-LICENSE-MIT
License-File: LICENSE_vsimd-LICENSE-MIT
License-File: LICENSE_walkdir-LICENSE-MIT
License-File: LICENSE_want-LICENSE-MIT
License-File: LICENSE_web-time-LICENSE-APACHE
License-File: LICENSE_web-time-LICENSE-MIT
License-File: LICENSE_webpki-roots-LICENSE
License-File: LICENSE_whoami-LICENSE-APACHE
License-File: LICENSE_whoami-LICENSE-BOOST
License-File: LICENSE_whoami-LICENSE-MIT
License-File: LICENSE_winnow-LICENSE-MIT
License-File: LICENSE_write16-LICENSE-APACHE
License-File: LICENSE_write16-LICENSE-MIT
License-File: LICENSE_wyz-LICENSE-MIT
License-File: LICENSE_xmlparser-LICENSE-APACHE
License-File: LICENSE_xmlparser-LICENSE-MIT
License-File: LICENSE_xxhash-rust-LICENSE-BOOST
License-File: LICENSE_xz2-LICENSE-APACHE
License-File: LICENSE_xz2-LICENSE-MIT
License-File: LICENSE_z85-LICENSE-APACHE
License-File: LICENSE_z85-LICENSE-MIT
License-File: LICENSE_zerocopy-LICENSE-APACHE
License-File: LICENSE_zerocopy-LICENSE-BSD
License-File: LICENSE_zerocopy-LICENSE-MIT
License-File: LICENSE_zerocopy-derive-LICENSE-APACHE
License-File: LICENSE_zerocopy-derive-LICENSE-BSD
License-File: LICENSE_zerocopy-derive-LICENSE-MIT
License-File: LICENSE_zeroize-LICENSE-APACHE
License-File: LICENSE_zeroize-LICENSE-MIT
License-File: LICENSE_zstd-LICENSE-MIT
License-File: LICENSE_zstd-safe-LICENSE-APACHE
License-File: LICENSE_zstd-safe-LICENSE-MIT
License-File: LICENSE_zstd-sys-LICENSE-APACHE
License-File: LICENSE_zstd-sys-LICENSE-MIT
Summary: Pathway is a data processing framework which takes care of streaming data updates for you.
Requires-Python: >=3.10
Project-URL: Documentation, https://pathway.com/developers/user-guide/introduction/welcome
Project-URL: Homepage, https://pathway.com/
Project-URL: Source code, https://github.com/pathwaycom/pathway/
Project-URL: Troubleshooting, https://pathway.com/troubleshooting/
